djangocms_versioning/__init__.py
djangocms_versioning/admin.py
djangocms_versioning/apps.py
djangocms_versioning/cms_config.py
djangocms_versioning/cms_menus.py
djangocms_versioning/cms_toolbars.py
djangocms_versioning/compat.py
djangocms_versioning/conditions.py
djangocms_versioning/conf.py
djangocms_versioning/constants.py
djangocms_versioning/datastructures.py
djangocms_versioning/emails.py
djangocms_versioning/exceptions.py
djangocms_versioning/forms.py
djangocms_versioning/handlers.py
djangocms_versioning/helpers.py
djangocms_versioning/indicators.py
djangocms_versioning/managers.py
djangocms_versioning/models.py
djangocms_versioning/operations.py
djangocms_versioning/plugin_rendering.py
djangocms_versioning/signals.py
djangocms_versioning/versionables.py
djangocms_versioning/locale/ar/LC_MESSAGES/django.mo
djangocms_versioning/locale/ar/LC_MESSAGES/django.po
djangocms_versioning/locale/de/LC_MESSAGES/django.mo
djangocms_versioning/locale/de/LC_MESSAGES/django.po
djangocms_versioning/locale/en/LC_MESSAGES/django.mo
djangocms_versioning/locale/en/LC_MESSAGES/django.po
djangocms_versioning/locale/fr/LC_MESSAGES/django.mo
djangocms_versioning/locale/fr/LC_MESSAGES/django.po
djangocms_versioning/locale/nl/LC_MESSAGES/django.mo
djangocms_versioning/locale/nl/LC_MESSAGES/django.po
djangocms_versioning/locale/ru/LC_MESSAGES/django.mo
djangocms_versioning/locale/ru/LC_MESSAGES/django.po
djangocms_versioning/locale/sq/LC_MESSAGES/django.mo
djangocms_versioning/locale/sq/LC_MESSAGES/django.po
djangocms_versioning/locale/zh_Hans/LC_MESSAGES/django.mo
djangocms_versioning/locale/zh_Hans/LC_MESSAGES/django.po
djangocms_versioning/management/__init__.py
djangocms_versioning/management/commands/__init__.py
djangocms_versioning/management/commands/create_versions.py
djangocms_versioning/migrations/0001_initial.py
djangocms_versioning/migrations/0002_delete_campaign.py
djangocms_versioning/migrations/0003_version.py
djangocms_versioning/migrations/0004_auto_20180730_1135.py
djangocms_versioning-2.5.0.dist-info/licenses/LICENSE.txt
djangocms_versioning-2.5.0.dist-info/METADATA
djangocms_versioning-2.5.0.dist-info/WHEEL
djangocms_versioning-2.5.0.dist-info/top_level.txt
djangocms_versioning-2.5.0.dist-info/RECORD
